dymfile/__init__.py
dymfile/_formats.py
dymfile/_utils.py
dymfile/backend.py
dymfile/cli.py
dymfile/reader.py
dymfile/writer.py
dymfile-0.2.0.dist-info/METADATA
dymfile-0.2.0.dist-info/WHEEL
dymfile-0.2.0.dist-info/entry_points.txt
dymfile-0.2.0.dist-info/RECORD
