Metadata-Version: 2.4
Name: dymfile
Version: 0.2.0
Summary: Read and write DYM file format from SEAPODYM project with xarray integration
Project-URL: Homepage, https://github.com/Ash12H/dymfile
Project-URL: Documentation, https://ash12h.github.io/dymfile
Project-URL: Repository, https://github.com/Ash12H/dymfile
Project-URL: Issues, https://github.com/Ash12H/dymfile/issues
Author-email: Ash <lehodey.jules@gmail.com>
License: MIT
Keywords: dym,netcdf,oceanography,seapodym,xarray
Classifier: Development Status :: 3 - Alpha
Classifier: Intended Audience :: Science/Research
Classifier: License :: OSI Approved :: MIT License
Classifier: Programming Language :: Python :: 3
Classifier: Programming Language :: Python :: 3.10
Classifier: Programming Language :: Python :: 3.11
Classifier: Programming Language :: Python :: 3.12
Classifier: Programming Language :: Python :: 3.13
Classifier: Topic :: Scientific/Engineering :: Oceanography
Requires-Python: >=3.10
Requires-Dist: numpy>=1.24.0
Requires-Dist: xarray>=2023.1.0
Provides-Extra: dev
Requires-Dist: pre-commit>=3.0.0; extra == 'dev'
Requires-Dist: pyright>=1.1.0; extra == 'dev'
Requires-Dist: pytest-cov>=4.0.0; extra == 'dev'
Requires-Dist: pytest>=7.0.0; extra == 'dev'
Requires-Dist: ruff>=0.8.0; extra == 'dev'
Provides-Extra: docs
Requires-Dist: mkdocs-material>=9.0.0; extra == 'docs'
Requires-Dist: mkdocs>=1.5.0; extra == 'docs'
Requires-Dist: mkdocstrings[python]>=0.24.0; extra == 'docs'
